txwebutils/__init__.py
txwebutils/encutils.py
txwebutils/csauth/__init__.py
txwebutils/csauth/cookies.py
txwebutils/csauth/cred.py
txwebutils/csauth/helper.py
txwebutils/csauth/icsauth.py
txwebutils/csauth/resources.py
txwebutils/tests/__init__.py
txwebutils/tests/test_csauth.py
txwebutils/tests/test_encutils.py
txwebutils-0.0.1.dist-info/METADATA
txwebutils-0.0.1.dist-info/WHEEL
txwebutils-0.0.1.dist-info/top_level.txt
txwebutils-0.0.1.dist-info/RECORD
