Metadata-Version: 2.1
Name: txwebutils
Version: 0.0.1
Summary: Utilities for twisted web
Home-page: https://github.com/bennr01/txwebutils/
Author: bennr01
Author-email: benjamin99.vogt@web.de
License: MIT
Keywords: twisted web utils unicode csauth xsauth
Platform: UNKNOWN
Classifier: License :: OSI Approved :: MIT License
Classifier: Topic :: Internet :: WWW/HTTP
Classifier: Development Status :: 3 - Alpha
Classifier: Framework :: Twisted
Classifier: Programming Language :: Python
Classifier: Programming Language :: Python :: 2.7
Classifier: Programming Language :: Python :: 3.8
Classifier: Programming Language :: Python :: 3.9
Requires-Dist: six
Requires-Dist: Twisted
Requires-Dist: zope.interface
Requires-Dist: treq
Requires-Dist: expiringdict
